digitalguide_reader/__init__.py
digitalguide_reader/gsheet2actions.py
digitalguide_reader/gsheet_utils.py
digitalguide_reader/upload_route.py
digitalguide_reader/standardinteraktion/Action.py
digitalguide_reader/standardinteraktion/Interaktion.py
digitalguide_reader/standardinteraktion/Route.py
digitalguide_reader/standardinteraktion/Trigger.py
digitalguide_reader/standardinteraktion/__init__.py
digitalguide_reader/standardinteraktion/wegInteraktion.py
digitalguide_reader-0.0.54.dist-info/licenses/LICENSE
digitalguide_reader-0.0.54.dist-info/METADATA
digitalguide_reader-0.0.54.dist-info/WHEEL
digitalguide_reader-0.0.54.dist-info/entry_points.txt
digitalguide_reader-0.0.54.dist-info/top_level.txt
digitalguide_reader-0.0.54.dist-info/RECORD
