Metadata-Version: 2.4
Name: digitalguide_reader
Version: 0.0.54
Summary: A Python Library to read in a google sheet and turn it into states and actions
Author: Soeren Etler
License: MIT
License-File: LICENSE
Requires-Dist: openpyxl
Requires-Dist: PyYAML
Requires-Dist: requests
Requires-Dist: google-api-python-client
Requires-Dist: google-auth-httplib2
Requires-Dist: google-auth-oauthlib
Dynamic: author
Dynamic: description
Dynamic: description-content-type
Dynamic: license
Dynamic: license-file
Dynamic: requires-dist
Dynamic: summary
